<?xml version="1.0" encoding="UTF-8" standalone="no"?>
<databaseChangeLog xmlns="http://www.liquibase.org/xml/ns/dbchangelog" xmlns:xsi="http://www.w3.org/2001/XMLSchema-instance"
                   xsi:schemaLocation="http://www.liquibase.org/xml/ns/dbchangelog http://www.liquibase.org/xml/ns/dbchangelog/dbchangelog-2.0.xsd">

    <changeSet id="1.0.3-insert-basic-values" author="Milko">
        <sql>INSERT INTO inputs (key_id, input) VALUES ((SELECT id FROM keys WHERE key='бира 3'), 'бира 3');</sql>
        <sql>INSERT INTO inputs (key_id, input) VALUES ((SELECT id FROM keys WHERE key='бира 3'), 'б 3');</sql>
        <sql>INSERT INTO inputs (key_id, input) VALUES ((SELECT id FROM keys WHERE key='бира 3'), 'b3');</sql>
        <sql>INSERT INTO inputs (key_id, input) VALUES ((SELECT id FROM keys WHERE key='бира 3'), 'b 3');</sql>
        <sql>INSERT INTO inputs (key_id, input) VALUES ((SELECT id FROM keys WHERE key='бира 3'), 'бира3');</sql>
        <sql>INSERT INTO inputs (key_id, input) VALUES ((SELECT id FROM keys WHERE key='бира 2.5'), 'бира 2.5');</sql>
        <sql>INSERT INTO inputs (key_id, input) VALUES ((SELECT id FROM keys WHERE key='бира 2.5'), 'б 2.5');</sql>
        <sql>INSERT INTO inputs (key_id, input) VALUES ((SELECT id FROM keys WHERE key='бира 2.5'), 'b2.5');</sql>
        <sql>INSERT INTO inputs (key_id, input) VALUES ((SELECT id FROM keys WHERE key='бира 2.5'), 'b 2.5');</sql>
        <sql>INSERT INTO inputs (key_id, input) VALUES ((SELECT id FROM keys WHERE key='бира 2.5'), 'бира2.5');</sql>
        <sql>INSERT INTO inputs (key_id, input) VALUES ((SELECT id FROM keys WHERE key='бира 2.5'), 'бира 2.5');</sql>
        <sql>INSERT INTO inputs (key_id, input) VALUES ((SELECT id FROM keys WHERE key='бира 2.5'), 'бира 2,5');</sql>
        <sql>INSERT INTO inputs (key_id, input) VALUES ((SELECT id FROM keys WHERE key='бира 2.5'), 'б 2,5');</sql>
        <sql>INSERT INTO inputs (key_id, input) VALUES ((SELECT id FROM keys WHERE key='бира 2.5'), 'b2,5');</sql>
        <sql>INSERT INTO inputs (key_id, input) VALUES ((SELECT id FROM keys WHERE key='бира 2.5'), 'b 2,5');</sql>
        <sql>INSERT INTO inputs (key_id, input) VALUES ((SELECT id FROM keys WHERE key='бира 2.5'), 'бира2,5');</sql>
        <sql>INSERT INTO inputs (key_id, input) VALUES ((SELECT id FROM keys WHERE key='бира 2.5'), 'бира 2,5');</sql>
        <sql>INSERT INTO inputs (key_id, input) VALUES ((SELECT id FROM keys WHERE key='бира 2'), 'бира 2');</sql>
        <sql>INSERT INTO inputs (key_id, input) VALUES ((SELECT id FROM keys WHERE key='бира 2'), 'б 2');</sql>
        <sql>INSERT INTO inputs (key_id, input) VALUES ((SELECT id FROM keys WHERE key='бира 2'), 'b2');</sql>
        <sql>INSERT INTO inputs (key_id, input) VALUES ((SELECT id FROM keys WHERE key='бира 2'), 'b 2');</sql>
        <sql>INSERT INTO inputs (key_id, input) VALUES ((SELECT id FROM keys WHERE key='бира 2'), 'бира2');</sql>
        <sql>INSERT INTO inputs (key_id, input) VALUES ((SELECT id FROM keys WHERE key='бира 2'), 'бира 2');</sql>
        <sql>INSERT INTO inputs (key_id, input) VALUES ((SELECT id FROM keys WHERE key='бира 0.5'), 'бира 0.5');</sql>
        <sql>INSERT INTO inputs (key_id, input) VALUES ((SELECT id FROM keys WHERE key='бира 0.5'), 'б 0.5');</sql>
        <sql>INSERT INTO inputs (key_id, input) VALUES ((SELECT id FROM keys WHERE key='бира 0.5'), 'b0.5');</sql>
        <sql>INSERT INTO inputs (key_id, input) VALUES ((SELECT id FROM keys WHERE key='бира 0.5'), 'b 0.5');</sql>
        <sql>INSERT INTO inputs (key_id, input) VALUES ((SELECT id FROM keys WHERE key='бира 0.5'), 'бира0.5');</sql>
        <sql>INSERT INTO inputs (key_id, input) VALUES ((SELECT id FROM keys WHERE key='бира 0.5'), 'бира 0.5');</sql>
        <sql>INSERT INTO inputs (key_id, input) VALUES ((SELECT id FROM keys WHERE key='бира 0.5'), 'бира 0,5');</sql>
        <sql>INSERT INTO inputs (key_id, input) VALUES ((SELECT id FROM keys WHERE key='бира 0.5'), 'б 0,5');</sql>
        <sql>INSERT INTO inputs (key_id, input) VALUES ((SELECT id FROM keys WHERE key='бира 0.5'), 'b0,5');</sql>
        <sql>INSERT INTO inputs (key_id, input) VALUES ((SELECT id FROM keys WHERE key='бира 0.5'), 'b 0,5');</sql>
        <sql>INSERT INTO inputs (key_id, input) VALUES ((SELECT id FROM keys WHERE key='бира 0.5'), 'бира0,5');</sql>
        <sql>INSERT INTO inputs (key_id, input) VALUES ((SELECT id FROM keys WHERE key='бира 0.5'), 'бира 0,5');</sql>
        <sql>INSERT INTO inputs (key_id, input) VALUES ((SELECT id FROM keys WHERE key='бира 0.33'), 'бира 0.33');</sql>
        <sql>INSERT INTO inputs (key_id, input) VALUES ((SELECT id FROM keys WHERE key='бира 0.33'), 'б 0.33');</sql>
        <sql>INSERT INTO inputs (key_id, input) VALUES ((SELECT id FROM keys WHERE key='бира 0.33'), 'b0.33');</sql>
        <sql>INSERT INTO inputs (key_id, input) VALUES ((SELECT id FROM keys WHERE key='бира 0.33'), 'b 0.33');</sql>
        <sql>INSERT INTO inputs (key_id, input) VALUES ((SELECT id FROM keys WHERE key='бира 0.33'), 'бира0.33');</sql>
        <sql>INSERT INTO inputs (key_id, input) VALUES ((SELECT id FROM keys WHERE key='бира 0.33'), 'бира 0.33');</sql>
        <sql>INSERT INTO inputs (key_id, input) VALUES ((SELECT id FROM keys WHERE key='бира 0.33'), 'бира 0,33');</sql>
        <sql>INSERT INTO inputs (key_id, input) VALUES ((SELECT id FROM keys WHERE key='бира 0.33'), 'б 0,33');</sql>
        <sql>INSERT INTO inputs (key_id, input) VALUES ((SELECT id FROM keys WHERE key='бира 0.33'), 'b0,33');</sql>
        <sql>INSERT INTO inputs (key_id, input) VALUES ((SELECT id FROM keys WHERE key='бира 0.33'), 'b 0,33');</sql>
        <sql>INSERT INTO inputs (key_id, input) VALUES ((SELECT id FROM keys WHERE key='бира 0.33'), 'бира0,33');</sql>
        <sql>INSERT INTO inputs (key_id, input) VALUES ((SELECT id FROM keys WHERE key='бира 0.33'), 'бира 0,33');</sql>
        <sql>INSERT INTO inputs (key_id, input) VALUES ((SELECT id FROM keys WHERE key='уиски 0.7'), 'у0.7');</sql>
        <sql>INSERT INTO inputs (key_id, input) VALUES ((SELECT id FROM keys WHERE key='уиски 0.7'), 'у 0.7');</sql>
        <sql>INSERT INTO inputs (key_id, input) VALUES ((SELECT id FROM keys WHERE key='уиски 0.7'), 'уиски 0.7');</sql>
        <sql>INSERT INTO inputs (key_id, input) VALUES ((SELECT id FROM keys WHERE key='уиски 0.7'), 'уиски0.7');</sql>
        <sql>INSERT INTO inputs (key_id, input) VALUES ((SELECT id FROM keys WHERE key='уиски 0.7'), 'w 0.7');</sql>
        <sql>INSERT INTO inputs (key_id, input) VALUES ((SELECT id FROM keys WHERE key='уиски 0.7'), 'w0.7');</sql>
        <sql>INSERT INTO inputs (key_id, input) VALUES ((SELECT id FROM keys WHERE key='уиски 0.7'), 'wiskey 0.7');</sql>
        <sql>INSERT INTO inputs (key_id, input) VALUES ((SELECT id FROM keys WHERE key='уиски 0.7'), 'wiskey0.7');</sql>
        <sql>INSERT INTO inputs (key_id, input) VALUES ((SELECT id FROM keys WHERE key='уиски 0.7'), 'у0,7');</sql>
        <sql>INSERT INTO inputs (key_id, input) VALUES ((SELECT id FROM keys WHERE key='уиски 0.7'), 'у 0,7');</sql>
        <sql>INSERT INTO inputs (key_id, input) VALUES ((SELECT id FROM keys WHERE key='уиски 0.7'), 'уиски 0,7');</sql>
        <sql>INSERT INTO inputs (key_id, input) VALUES ((SELECT id FROM keys WHERE key='уиски 0.7'), 'уиски0,7');</sql>
        <sql>INSERT INTO inputs (key_id, input) VALUES ((SELECT id FROM keys WHERE key='уиски 0.7'), 'w 0,7');</sql>
        <sql>INSERT INTO inputs (key_id, input) VALUES ((SELECT id FROM keys WHERE key='уиски 0.7'), 'w0,7');</sql>
        <sql>INSERT INTO inputs (key_id, input) VALUES ((SELECT id FROM keys WHERE key='уиски 0.7'), 'wiskey 0,7');</sql>
        <sql>INSERT INTO inputs (key_id, input) VALUES ((SELECT id FROM keys WHERE key='уиски 0.7'), 'wiskey0,7');</sql>
        <sql>INSERT INTO inputs (key_id, input) VALUES ((SELECT id FROM keys WHERE key='уиски 1'), 'у1');</sql>
        <sql>INSERT INTO inputs (key_id, input) VALUES ((SELECT id FROM keys WHERE key='уиски 1'), 'у 1');</sql>
        <sql>INSERT INTO inputs (key_id, input) VALUES ((SELECT id FROM keys WHERE key='уиски 1'), 'уиски 1');</sql>
        <sql>INSERT INTO inputs (key_id, input) VALUES ((SELECT id FROM keys WHERE key='уиски 1'), 'уиски1');</sql>
        <sql>INSERT INTO inputs (key_id, input) VALUES ((SELECT id FROM keys WHERE key='уиски 1'), 'w 1');</sql>
        <sql>INSERT INTO inputs (key_id, input) VALUES ((SELECT id FROM keys WHERE key='уиски 1'), 'w1');</sql>
        <sql>INSERT INTO inputs (key_id, input) VALUES ((SELECT id FROM keys WHERE key='уиски 1'), 'wiskey 1');</sql>
        <sql>INSERT INTO inputs (key_id, input) VALUES ((SELECT id FROM keys WHERE key='уиски 1'), 'wiskey1');</sql>
        <sql>INSERT INTO inputs (key_id, input) VALUES ((SELECT id FROM keys WHERE key='ракия 0.5'), 'ракия 0.5');</sql>
        <sql>INSERT INTO inputs (key_id, input) VALUES ((SELECT id FROM keys WHERE key='ракия 0.5'), 'ракия0.5');</sql>
        <sql>INSERT INTO inputs (key_id, input) VALUES ((SELECT id FROM keys WHERE key='ракия 0.5'), 'р0.5');</sql>
        <sql>INSERT INTO inputs (key_id, input) VALUES ((SELECT id FROM keys WHERE key='ракия 0.5'), 'р 0.5');</sql>
        <sql>INSERT INTO inputs (key_id, input) VALUES ((SELECT id FROM keys WHERE key='ракия 0.5'), 'r0.5');</sql>
        <sql>INSERT INTO inputs (key_id, input) VALUES ((SELECT id FROM keys WHERE key='ракия 0.5'), 'r 0.5');</sql>
        <sql>INSERT INTO inputs (key_id, input) VALUES ((SELECT id FROM keys WHERE key='ракия 0.5'), 'рак0.5');</sql>
        <sql>INSERT INTO inputs (key_id, input) VALUES ((SELECT id FROM keys WHERE key='ракия 0.5'), 'рак 0.5');</sql>
        <sql>INSERT INTO inputs (key_id, input) VALUES ((SELECT id FROM keys WHERE key='ракия 0.5'), 'rak 0.5');</sql>
        <sql>INSERT INTO inputs (key_id, input) VALUES ((SELECT id FROM keys WHERE key='ракия 0.5'), 'rak 0.5');</sql>
        <sql>INSERT INTO inputs (key_id, input) VALUES ((SELECT id FROM keys WHERE key='ракия 0.5'), 'ракия 0,5');</sql>
        <sql>INSERT INTO inputs (key_id, input) VALUES ((SELECT id FROM keys WHERE key='ракия 0.5'), 'ракия0,5');</sql>
        <sql>INSERT INTO inputs (key_id, input) VALUES ((SELECT id FROM keys WHERE key='ракия 0.5'), 'р0,5');</sql>
        <sql>INSERT INTO inputs (key_id, input) VALUES ((SELECT id FROM keys WHERE key='ракия 0.5'), 'р 0,5');</sql>
        <sql>INSERT INTO inputs (key_id, input) VALUES ((SELECT id FROM keys WHERE key='ракия 0.5'), 'r0,5');</sql>
        <sql>INSERT INTO inputs (key_id, input) VALUES ((SELECT id FROM keys WHERE key='ракия 0.5'), 'r 0,5');</sql>
        <sql>INSERT INTO inputs (key_id, input) VALUES ((SELECT id FROM keys WHERE key='ракия 0.5'), 'рак0,5');</sql>
        <sql>INSERT INTO inputs (key_id, input) VALUES ((SELECT id FROM keys WHERE key='ракия 0.5'), 'рак 0,5');</sql>
        <sql>INSERT INTO inputs (key_id, input) VALUES ((SELECT id FROM keys WHERE key='ракия 0.5'), 'rak 0,5');</sql>
        <sql>INSERT INTO inputs (key_id, input) VALUES ((SELECT id FROM keys WHERE key='ракия 0.5'), 'rak 0,5');</sql>
        <sql>INSERT INTO inputs (key_id, input) VALUES ((SELECT id FROM keys WHERE key='ракия 1'), 'ракия 1');</sql>
        <sql>INSERT INTO inputs (key_id, input) VALUES ((SELECT id FROM keys WHERE key='ракия 1'), 'ракия1');</sql>
        <sql>INSERT INTO inputs (key_id, input) VALUES ((SELECT id FROM keys WHERE key='ракия 1'), 'р1');</sql>
        <sql>INSERT INTO inputs (key_id, input) VALUES ((SELECT id FROM keys WHERE key='ракия 1'), 'р 1');</sql>
        <sql>INSERT INTO inputs (key_id, input) VALUES ((SELECT id FROM keys WHERE key='ракия 1'), 'r1');</sql>
        <sql>INSERT INTO inputs (key_id, input) VALUES ((SELECT id FROM keys WHERE key='ракия 1'), 'r 1');</sql>
        <sql>INSERT INTO inputs (key_id, input) VALUES ((SELECT id FROM keys WHERE key='ракия 1'), 'рак1');</sql>
        <sql>INSERT INTO inputs (key_id, input) VALUES ((SELECT id FROM keys WHERE key='ракия 1'), 'рак 1');</sql>
        <sql>INSERT INTO inputs (key_id, input) VALUES ((SELECT id FROM keys WHERE key='ракия 1'), 'rak 1');</sql>
        <sql>INSERT INTO inputs (key_id, input) VALUES ((SELECT id FROM keys WHERE key='ракия 1'), 'rak 1');</sql>
        <sql>INSERT INTO inputs (key_id, input) VALUES ((SELECT id FROM keys WHERE key='вино 1'), 'вино 1');</sql>
        <sql>INSERT INTO inputs (key_id, input) VALUES ((SELECT id FROM keys WHERE key='вино 1'), 'вино1');</sql>
        <sql>INSERT INTO inputs (key_id, input) VALUES ((SELECT id FROM keys WHERE key='вино 1'), 'в1');</sql>
        <sql>INSERT INTO inputs (key_id, input) VALUES ((SELECT id FROM keys WHERE key='вино 1'), 'в 1');</sql>
        <sql>INSERT INTO inputs (key_id, input) VALUES ((SELECT id FROM keys WHERE key='вино 1'), 'wine 1');</sql>
        <sql>INSERT INTO inputs (key_id, input) VALUES ((SELECT id FROM keys WHERE key='вино 1'), 'wine1');</sql>
        <sql>INSERT INTO inputs (key_id, input) VALUES ((SELECT id FROM keys WHERE key='вино 3'), 'вино 3');</sql>
        <sql>INSERT INTO inputs (key_id, input) VALUES ((SELECT id FROM keys WHERE key='вино 3'), 'вино3');</sql>
        <sql>INSERT INTO inputs (key_id, input) VALUES ((SELECT id FROM keys WHERE key='вино 3'), 'в3');</sql>
        <sql>INSERT INTO inputs (key_id, input) VALUES ((SELECT id FROM keys WHERE key='вино 3'), 'в 3');</sql>
        <sql>INSERT INTO inputs (key_id, input) VALUES ((SELECT id FROM keys WHERE key='вино 3'), 'wine 3');</sql>
        <sql>INSERT INTO inputs (key_id, input) VALUES ((SELECT id FROM keys WHERE key='вино 3'), 'wine3');</sql>
    </changeSet>
</databaseChangeLog>